{
    "archive": "DAKhmO",
    "archivedAt": [
        "https://www.familysearch.org/records/images/beta/search-results?imageGroupNumbers=115459777"
    ],
    "csvUrl": "https://docs.google.com/spreadsheets/d/e/2PACX-1vR6bNkg7DNsC03Tll6L08aPB0QDdkawAXy1WyTJ80f6o-ivjFQZYhhxwKzmQbg3qciRGkY5dD0Im_re/pub?gid=1532887418&single=true&output=csv",
    "dateCreated": "1865",
    "dateModified": "1954-11-22",
    "genre": "Parish register",
    "gssUrl": "https://docs.google.com/spreadsheets/d/179ruM_6avxqK1m4s_dY6yUGzzeK3Pz-u9yAIFNHOuFg/edit?usp=sharing",
    "identifier": "315-1-8724",
    "documentLocale": "ru", "tableLocale": "ru",
    "isPartial": true,
    "title": "Метрическая книга регистрации актов о рождении, браке и смерти по церкви с. Отченашевки, Ямпольского уезда за 1865 г."
}