{
    "archive": "DAZhO",
    "archivedAt": [
        "https://uk.wikisource.org/wiki/%D0%90%D1%80%D1%85%D1%96%D0%B2:%D0%94%D0%90%D0%96%D0%9E/1/75/113"
    ],
    "csvUrl": "https://docs.google.com/spreadsheets/d/e/2PACX-1vSQI_HqYPR9gV3PZr3K35AJqoAly3tDvhIdRAwMJTJ44uMZKjR1iaF1AhgyQjKVfTlpH7BXtx-pzf-O/pub?gid=262948730&single=true&output=csv",
    "dateCreated": "1862",
    "documentLocale": "ru",
    "genre": "Unstructured",
    "gssUrl": "https://docs.google.com/spreadsheets/d/1tWUgjeSkXW1Wd7OhF-u-i34MTN8z_IvIJpRwWwfJ2Yo/edit?usp=sharing",
    "identifier": "1-75-113",
    "isPartial": true,
    "tableLocale": "uk",
    "title": "Церк. метр. книга Новоград-Волинського повіту, 1862 р."
  }
  